LICENSE
README.md
setup.py
coindesk_scraper/__init__.py
coindesk_scraper.egg-info/PKG-INFO
coindesk_scraper.egg-info/SOURCES.txt
coindesk_scraper.egg-info/dependency_links.txt
coindesk_scraper.egg-info/requires.txt
coindesk_scraper.egg-info/top_level.txt