Metadata-Version: 2.1
Name: coindesk-scraper
Version: 1.0.1
Summary: A python library to scrape Coindesk
Home-page: UNKNOWN
Author: DataKund
Author-email: datakund@gmail.com
License: Apache License 2.0
Keywords: coindesk,python,bot_studio,automation,search,scraper,scrape
Platform: UNKNOWN
License-File: LICENSE
